AUTHORS
ChangeLog
LICENSE
MANIFEST.in
NOTICE
README.rst
requirements.txt
setup.py
tox.ini
docs/Makefile
docs/api.rst
docs/channel.rst
docs/conf.py
docs/design.rst
docs/event.rst
docs/examples.rst
docs/ext.rst
docs/futures.rst
docs/index.rst
docs/io.rst
docs/lib.rst
docs/local.rst
docs/locks.rst
docs/loop.rst
docs/make.bat
docs/patcher.rst
docs/queue.rst
docs/tasks.rst
docs/timeout.rst
evergreen/__init__.py
evergreen/channel.py
evergreen/event.py
evergreen/local.py
evergreen/locks.py
evergreen/log.py
evergreen/patcher.py
evergreen/queue.py
evergreen/six.py
evergreen/tasks.py
evergreen/timeout.py
evergreen.egg-info/PKG-INFO
evergreen.egg-info/SOURCES.txt
evergreen.egg-info/dependency_links.txt
evergreen.egg-info/requires.txt
evergreen.egg-info/top_level.txt
evergreen/core/__init__.py
evergreen/core/loop.py
evergreen/core/socketpair.py
evergreen/core/threadpool.py
evergreen/ext/__init__.py
evergreen/futures/__init__.py
evergreen/futures/_base.py
evergreen/futures/_process.py
evergreen/futures/_task.py
evergreen/futures/_thread.py
evergreen/io/__init__.py
evergreen/io/errno.py
evergreen/io/fs.py
evergreen/io/pipe.py
evergreen/io/stream.py
evergreen/io/tcp.py
evergreen/io/tty.py
evergreen/io/udp.py
evergreen/io/util.py
evergreen/lib/__init__.py
evergreen/lib/select.py
evergreen/lib/socket.py
evergreen/lib/ssl.py
evergreen/lib/time.py
examples/crawler.py
examples/echo-server.py
tests/.test_io.py.swp
tests/common.py
tests/test_channel.py
tests/test_event.py
tests/test_futures.py
tests/test_io.py
tests/test_local.py
tests/test_locks.py
tests/test_loop.py
tests/test_tasks.py
tests/test_timeout.py