Metadata-Version: 1.1
Name: evergreen
Version: 0.1.0
Summary: Cooperative multitasking and i/o for Python
Home-page: http://github.com/saghul/evergreen
Author: Saúl Ibarra Corretgé
Author-email: saghul@gmail.com
License: UNKNOWN
Platform: POSIX
Platform: Microsoft Windows
Classifier: Development Status :: 3 - Alpha
Classifier: Intended Audience :: Developers
Classifier: License :: OSI Approved :: MIT License
Classifier: Operating System :: POSIX
Classifier: Operating System :: Microsoft :: Windows
Classifier: Programming Language :: Python
Classifier: Programming Language :: Python :: 2
Classifier: Programming Language :: Python :: 2.6
Classifier: Programming Language :: Python :: 2.7
Classifier: Programming Language :: Python :: 3
Classifier: Programming Language :: Python :: 3.2
Classifier: Programming Language :: Python :: 3.3
